zappa_django_utils/__init__.py
zappa_django_utils/admin.py
zappa_django_utils/models.py
zappa_django_utils/urls.py
zappa_django_utils/views.py
zappa_django_utils/db/__init__.py
zappa_django_utils/db/backends/__init__.py
zappa_django_utils/db/backends/s3sqlite/__init__.py
zappa_django_utils/db/backends/s3sqlite/base.py
zappa_django_utils/db/backends/s3sqlite/client.py
zappa_django_utils/db/backends/s3sqlite/features.py
zappa_django_utils/management/__init__.py
zappa_django_utils/management/commands/__init__.py
zappa_django_utils/management/commands/create_admin_user.py
zappa_django_utils/management/commands/create_mysql_db.py
zappa_django_utils/management/commands/create_pg_db.py
zappa_django_utils/management/commands/create_pg_schema.py
zappa_django_utils/management/commands/drop_pg_db.py
zappa_django_utils/management/commands/drop_pg_schema.py
zappa_django_utils/management/commands/s3sqlite_vacuum.py
zappa_django_utils/migrations/__init__.py
zappa_django_utils-0.4.1.dist-info/LICENSE
zappa_django_utils-0.4.1.dist-info/METADATA
zappa_django_utils-0.4.1.dist-info/WHEEL
zappa_django_utils-0.4.1.dist-info/top_level.txt
zappa_django_utils-0.4.1.dist-info/RECORD
